kp_ssf_tools/__init__.py
kp_ssf_tools/py.typed
kp_ssf_tools/analyze/__init__.py
kp_ssf_tools/analyze/models/__init__.py
kp_ssf_tools/analyze/models/analysis.py
kp_ssf_tools/analyze/models/configuration.py
kp_ssf_tools/analyze/models/content_aware.py
kp_ssf_tools/analyze/models/types.py
kp_ssf_tools/analyze/services/__init__.py
kp_ssf_tools/analyze/services/detect_secrets_service.py
kp_ssf_tools/analyze/services/interfaces.py
kp_ssf_tools/analyze/services/threshold_service.py
kp_ssf_tools/analyze/services/entropy/__init__.py
kp_ssf_tools/analyze/services/entropy/analyzer.py
kp_ssf_tools/cli/__init__.py
kp_ssf_tools/cli/main.py
kp_ssf_tools/cli/commands/__init__.py
kp_ssf_tools/cli/commands/analyze.py
kp_ssf_tools/cli/commands/cache.py
kp_ssf_tools/cli/commands/config.py
kp_ssf_tools/cli/commands/utils.py
kp_ssf_tools/cli/commands/volatility.py
kp_ssf_tools/cli/utils/__init__.py
kp_ssf_tools/cli/utils/version_checker.py
kp_ssf_tools/containers/__init__.py
kp_ssf_tools/containers/analysis.py
kp_ssf_tools/containers/application.py
kp_ssf_tools/containers/core.py
kp_ssf_tools/containers/entropy.py
kp_ssf_tools/core/__init__.py
kp_ssf_tools/core/rich_helpers.py
kp_ssf_tools/core/utils.py
kp_ssf_tools/core/services/__init__.py
kp_ssf_tools/core/services/cache/__init__.py
kp_ssf_tools/core/services/cache/interfacecs.py
kp_ssf_tools/core/services/cache/models.py
kp_ssf_tools/core/services/cache/service.py
kp_ssf_tools/core/services/config/__init__.py
kp_ssf_tools/core/services/config/interfaces.py
kp_ssf_tools/core/services/config/manager.py
kp_ssf_tools/core/services/config/models.py
kp_ssf_tools/core/services/config/service.py
kp_ssf_tools/core/services/config/types.py
kp_ssf_tools/core/services/excel_export/__init__.py
kp_ssf_tools/core/services/excel_export/formatting.py
kp_ssf_tools/core/services/excel_export/interfaces.py
kp_ssf_tools/core/services/excel_export/service.py
kp_ssf_tools/core/services/excel_export/sheet_management.py
kp_ssf_tools-0.2.0.dist-info/licenses/LICENSE.txt
kp_ssf_tools-0.2.0.dist-info/licenses/NOTICE
kp_ssf_tools-0.2.0.dist-info/METADATA
kp_ssf_tools-0.2.0.dist-info/WHEEL
kp_ssf_tools-0.2.0.dist-info/entry_points.txt
kp_ssf_tools-0.2.0.dist-info/top_level.txt
kp_ssf_tools-0.2.0.dist-info/RECORD
