Metadata-Version: 2.4
Name: kp-ssf-tools
Version: 0.2.0
Summary: SSF Tools - Forensic Analysis Toolkit for cybersecurity professionals
Author-email: KirkpatrickPrice <info@kirkpatrickprice.com>
License-Expression: Apache-2.0
Project-URL: Homepage, https://github.com/kirkpatrickprice/ssf-tools
Project-URL: Repository, https://github.com/kirkpatrickprice/ssf-tools
Project-URL: Issues, https://github.com/kirkpatrickprice/ssf-tools/issues
Keywords: forensics,cybersecurity,volatility,memory-analysis
Classifier: Development Status :: 3 - Alpha
Classifier: Intended Audience :: Information Technology
Classifier: Operating System :: OS Independent
Classifier: Programming Language :: Python :: 3
Classifier: Programming Language :: Python :: 3.13
Classifier: Topic :: Security
Classifier: Topic :: System :: Systems Administration
Requires-Python: >=3.13
License-File: LICENSE.txt
License-File: NOTICE
Requires-Dist: rich>=13.0.0
Requires-Dist: rich-click>=1.7.0
Requires-Dist: click>=8.0.0
Requires-Dist: pydantic>=2.11.7
Requires-Dist: dependency-injector>=4.41.0
Requires-Dist: httpx>=0.27.0
Requires-Dist: platformdirs>=4.3.8
Requires-Dist: puremagic>=1.30
Requires-Dist: python-magic>=0.4.27
Requires-Dist: python-magic-bin>=0.4.14; sys_platform == "win32"
Requires-Dist: pyyaml>=6.0.2
Requires-Dist: pygments>=2.19.2
Requires-Dist: charset-normalizer>=3.4.3
Requires-Dist: openpyxl>=3.1.5
Requires-Dist: pandas>=2.3.2
Requires-Dist: xlsxwriter>=3.2.5
Requires-Dist: detect-secrets>=1.5.0
Requires-Dist: volatility3[full]>=2.26.0
Provides-Extra: docs
Requires-Dist: mkdocs>=1.6.0; extra == "docs"
Requires-Dist: mkdocs-material>=9.5.0; extra == "docs"
Requires-Dist: mkdocstrings[python]>=0.26.0; extra == "docs"
Requires-Dist: mkdocs-gen-files>=0.5.0; extra == "docs"
Requires-Dist: mkdocs-literate-nav>=0.6.0; extra == "docs"
Requires-Dist: mkdocs-section-index>=0.3.0; extra == "docs"
Requires-Dist: mkdocs-autorefs>=1.0.0; extra == "docs"
Requires-Dist: pymdown-extensions>=10.0.0; extra == "docs"
Requires-Dist: mkdocs-git-revision-date-localized-plugin>=1.2.0; extra == "docs"
Requires-Dist: mkdocs-mermaid2-plugin>=1.2.1; extra == "docs"
Requires-Dist: kp-ssf-tools; extra == "docs"
Dynamic: license-file
